<?xml version="1.0" encoding="utf-16"?>
<StatsConfig xmlns:xsd="http://www.w3.org/2001/XMLSchema" xmlns:xsi="http://www.w3.org/2001/XMLSchema-instance">
  <WATER_USAGE>0.03</WATER_USAGE>
  <FOOD_USAGE>0.015</FOOD_USAGE>
  <SLEEP_USAGE>0.01</SLEEP_USAGE>
  <WATER_DAMAGE>3</WATER_DAMAGE>
  <FOOD_DAMAGE>1.5</FOOD_DAMAGE>
  <SLEEP_DAMAGE>1</SLEEP_DAMAGE>
  <SLEEP_GAIN_SITTING>0.5</SLEEP_GAIN_SITTING>
  <SLEEP_GAIN_SLEEPING>34</SLEEP_GAIN_SLEEPING>
  <RESPAWN_WATER>10</RESPAWN_WATER>
  <RESPAWN_FOOD>10</RESPAWN_FOOD>
  <RESPAWN_SLEEP>10</RESPAWN_SLEEP>
</StatsConfig>